Design.v
module PIPO(
   input [3:0]din_i, 
   input load_i, 
   input clk_i, 
   input rst_i, 
   output reg [3:0]dout_o
);

//net(s)
reg [3:0]DATA;
always@(posedge clk_i) begin
   if(rst_i)
      dout_o <= 1'b0;
   else if(load_i) begin
      dout_o <= din_i;
   end
end

endmodule

Testbench.v
module tb_PIPO();
reg load_ti;
reg clk_ti = 1'b0;
reg [3:0]din_ti;
reg rst_ti;
wire [3:0]dout_to;

//instantiation
PIPO DUT(.din_i(din_ti), 
   .load_i(load_ti), 
   .clk_i(clk_ti), 
   .rst_i(rst_ti), 
   .dout_o(dout_to));

//clock
initial begin
   forever
      #5 clk_ti = ~clk_ti;
end

//feeding
initial begin
rst_ti = 1'b1;
load_ti = 1'b0;
din_ti = 4'b0000;
#10 rst_ti = 1'b0;
    load_ti = 1'b1;
    din_ti = 4'b1010;
#10 load_ti = 1'b0;
    din_ti = 4'b1111;
#20 load_ti = 1'b1;
#10 load_ti = 1'b0;
#10 $finish;
end

//capture
initial begin
$monitor("Time: %0t | Load: %b, Clk: %b | Input: %h | Output: %h", $time, load_ti, clk_ti, din_ti, dout_to);
$dumpfile("PIPO.vcd");
$dumpvars(0, tb_PIPO);
end
endmodule

PIPO.vcd
$date
   Sat May  9 10:25:43 2026
$end

$version
  2025.2
  $dumpfile ("PIPO.vcd") 
$end

$timescale
  1ps
$end

$scope module tb_PIPO $end
$var reg 1 ! load_ti $end
$var reg 1 " clk_ti $end
$var reg 4 # din_ti [3:0] $end
$var reg 1 $ rst_ti $end
$var wire 4 % dout_to [3:0] $end
$scope module DUT $end
$var wire 4 & din_i [3:0] $end
$var wire 1 ' load_i $end
$var wire 1 ( clk_i $end
$var wire 1 ) rst_i $end
$var reg 4 * dout_o [3:0] $end
$var reg 4 + DATA [3:0] $end
$upscope $end
$upscope $end
$enddefinitions $end

#0
$dumpvars
0!
0"
b0 #
1$
bx %
b0 &
0'
0(
1)
bx *
bx +
$end

#5000
1"
b0 %
1(
b0 *

#10000
1!
0"
b1010 #
0$
b1010 &
1'
0(
0)

#15000
1"
b1010 %
1(
b1010 *

#20000
0!
0"
b1111 #
b1111 &
0'
0(

#25000
1"
1(

#30000
0"
0(

#35000
1"
1(

#40000
1!
0"
1'
0(

#45000
1"
b1111 %
1(
b1111 *

#50000
0!
0"
0'
0(

